{
  "quiz": {
    "title": "High-School Geometry: Unit 12 Quiz 10",
    "subtitle": "Final Exam Preparation and Course Reflection",
    "subject": "Geometry",
    "topic": "Geometry: 12.10 Final Assessment and Portfolio Review",
    "duration": 30,
    "questions": [
      {
        "type": "mcq",
        "question": "In $\\triangle ABC$, $\\overline{DE} \\parallel \\overline{BC}$, with $D$ on $\\overline{AB}$ and $E$ on $\\overline{AC}$. $AD = x + 2$, $DB = 2x - 1$, $AE = 6$, and $EC = 9$. Find the value of $x$.",
        "options": [
          "$8$",
          "$4$",
          "$6$",
          "$10$"
        ],
        "answer": "A",
        "explanation": "By the Triangle Proportionality Theorem: $\\frac{AD}{DB} = \\frac{AE}{EC}$. So $\\frac{x + 2}{2x - 1} = \\frac{6}{9} = \\frac{2}{3}$. Cross-multiplying: $3(x + 2) = 2(2x - 1)$, giving $3x + 6 = 4x - 2$, so $x = 8$. Check: $AD = 10$, $DB = 15$, ratio $= \\frac{2}{3}$. ✓"
      },
      {
        "type": "mcq",
        "question": "In right $\\triangle PQR$ with right angle at $R$, altitude $\\overline{RS}$ is drawn to hypotenuse $\\overline{PQ}$. $PS = 3$ and $SQ = 12$. Find $PR$.",
        "options": [
          "$3\\sqrt{5}$",
          "$6$",
          "$3\\sqrt{3}$",
          "$9$"
        ],
        "answer": "A",
        "explanation": "$PR$ is a leg of the original triangle, adjacent to segment $PS$. Using the leg rule: $PR = \\sqrt{PQ \\cdot PS}$. $PQ = PS + SQ = 3 + 12 = 15$. So $PR = \\sqrt{15 \\cdot 3} = \\sqrt{45} = 3\\sqrt{5}$."
      },
      {
        "type": "mcq",
        "question": "A $25$-foot ladder leans against a building. The base of the ladder is $7$ feet from the building. What angle does the ladder make with the ground, rounded to the nearest degree?",
        "options": [
          "$74^\\circ$",
          "$16^\\circ$",
          "$60^\\circ$",
          "$30^\\circ$"
        ],
        "answer": "A",
        "explanation": "The ladder is the hypotenuse ($25$), the distance to the building is adjacent to the ground angle ($7$). $\\cos \\theta = \\frac{7}{25} = 0.28$. $\\theta = \\cos^{-1}(0.28) \\approx 73.7^\\circ \\approx 74^\\circ$. The ladder reaches $\\sqrt{25^2 - 7^2} = 24$ feet up the wall."
      },
      {
        "type": "mcq",
        "question": "In $\\triangle ABC$, $\\angle A = 35^\\circ$, $\\angle B = 80^\\circ$, and side $c$ (opposite $\\angle C$) $= 24$. Using the Law of Sines, find side $a$, rounded to the nearest tenth.",
        "options": [
          "$15.2$",
          "$18.7$",
          "$12.4$",
          "$20.1$"
        ],
        "answer": "A",
        "explanation": "$\\angle C = 180^\\circ - 35^\\circ - 80^\\circ = 65^\\circ$. Law of Sines: $\\frac{\\sin A}{a} = \\frac{\\sin C}{c}$, so $\\frac{\\sin 35^\\circ}{a} = \\frac{\\sin 65^\\circ}{24}$. $a = \\frac{24 \\cdot \\sin 35^\\circ}{\\sin 65^\\circ} \\approx \\frac{24 \\cdot 0.5736}{0.9063} \\approx 15.2$."
      },
      {
        "type": "mcq",
        "question": "A regular pentagon has side length $8$ cm and apothem $5.5$ cm. What is its area?",
        "options": [
          "$110$ cm$^2$",
          "$220$ cm$^2$",
          "$88$ cm$^2$",
          "$176$ cm$^2$"
        ],
        "answer": "A",
        "explanation": "Perimeter $= 5 \\times 8 = 40$ cm. Area $= \\frac{1}{2}aP = \\frac{1}{2} \\times 5.5 \\times 40 = 110$ cm$^2$. The regular polygon formula $A = \\frac{1}{2}aP$ works for any regular polygon."
      },
      {
        "type": "mcq",
        "question": "A cone has radius $5$ cm and slant height $13$ cm. What is its total surface area in terms of $\\pi$?",
        "options": [
          "$90\\pi$ cm$^2$",
          "$65\\pi$ cm$^2$",
          "$115\\pi$ cm$^2$",
          "$40\\pi$ cm$^2$"
        ],
        "answer": "A",
        "explanation": "Lateral area $= \\pi r\\ell = \\pi(5)(13) = 65\\pi$ cm$^2$. Base area $= \\pi r^2 = 25\\pi$ cm$^2$. Total $= 65\\pi + 25\\pi = 90\\pi$ cm$^2$. The vertical height is $\\sqrt{13^2 - 5^2} = 12$ cm, but surface area uses slant height."
      },
      {
        "type": "mcq",
        "question": "A sphere and a cylinder have the same radius $r$. The cylinder's height equals its diameter. What is the ratio of the sphere's volume to the cylinder's volume?",
        "options": [
          "$\\frac{2}{3}$",
          "$\\frac{1}{2}$",
          "$\\frac{1}{3}$",
          "$\\frac{3}{4}$"
        ],
        "answer": "A",
        "explanation": "Sphere: $V = \\frac{4}{3}\\pi r^3$. Cylinder: $h = 2r$, so $V = \\pi r^2(2r) = 2\\pi r^3$. Ratio $= \\frac{\\frac{4}{3}\\pi r^3}{2\\pi r^3} = \\frac{4/3}{2} = \\frac{2}{3}$. The sphere's volume is exactly $\\frac{2}{3}$ of the cylinder's volume."
      },
      {
        "type": "mcq",
        "question": "A rectangle with vertices $(0, 0)$, $(6, 0)$, $(6, 4)$, $(0, 4)$ is dilated about the origin by $k = 1.5$, then rotated $90^\\circ$ counterclockwise. What is the area of the final image?",
        "options": [
          "$54$ square units",
          "$24$ square units",
          "$36$ square units",
          "$48$ square units"
        ],
        "answer": "A",
        "explanation": "Original area $= 6 \\times 4 = 24$ square units. Dilation by $k = 1.5$ scales area by $k^2 = 2.25$: $24 \\times 2.25 = 54$ square units. Rotation is a rigid motion — it does not change area. The final area is $54$ square units."
      },
      {
        "type": "mcq",
        "question": "A cylindrical water tank has diameter $10$ ft and height $8$ ft. Water weighs $62.4$ lb/ft$^3$. What is the weight of water when the tank is completely full, rounded to the nearest hundred pounds?",
        "options": [
          "$39{,}200$ pounds",
          "$19{,}600$ pounds",
          "$78{,}400$ pounds",
          "$15{,}700$ pounds"
        ],
        "answer": "A",
        "explanation": "Radius $= 5$ ft. Volume $= \\pi(5^2)(8) = 200\\pi \\approx 628.32$ ft$^3$. Weight $= 62.4 \\times 628.32 \\approx 39{,}207 \\approx 39{,}200$ pounds (about $19.6$ tons)."
      },
      {
        "type": "mcq",
        "question": "In the coordinate plane, point $P(3, -4)$ is reflected across the line $y = x$, then translated by $\\langle -2, 5 \\rangle$. What are the final coordinates?",
        "options": [
          "$P''(-6, 8)$",
          "$P''(-4, 3)$",
          "$P''(1, 1)$",
          "$P''(6, -8)$"
        ],
        "answer": "A",
        "explanation": "Step 1 — Reflect across $y = x$: $(3, -4) \\rightarrow (-4, 3)$. Step 2 — Translate by $\\langle -2, 5 \\rangle$: $(-4, 3) \\rightarrow (-4 - 2, 3 + 5) = (-6, 8)$. The composition of a reflection and a translation is a glide reflection if the translation is parallel to the line of reflection, but here it is not, so it's just a general composition."
      }
    ],
    "settings": {
      "timeLimit": 30,
      "shuffleQuestions": true,
      "shuffleOptions": true,
      "showResults": true,
      "allowRetry": true
    },
    "grading": {
      "scoreMessages": {
        "90": "Outstanding! You have demonstrated mastery across the entire geometry curriculum — proofs and congruence, similarity, trigonometry, area and volume, transformations, and real-world applications. You are well-prepared for any final exam.",
        "70": "Good work across the course! This final review covered triangle proportionality, right triangle geometry, Law of Sines, regular polygon area, surface area and volume of cones and spheres, composite transformations, and density. Review any missed topics before the exam.",
        "50": "A fair performance on this comprehensive review. Focus on: (1) Triangle Proportionality and geometric mean relationships, (2) Law of Sines vs. Law of Cosines, (3) distinguishing slant height from vertical height, (4) area scaling by $k^2$ and volume by $k^3$, (5) composition order in transformations.",
        "0": "This final assessment spans the full geometry course. Key areas to review: triangle theorems (proportionality, angle bisector), similarity and scale factors, right triangle trigonometry and Laws of Sines/Cosines, area and volume of all solids, transformations (translations, reflections, rotations, dilations, compositions), and real-world applications. Practice each area systematically."
      }
    }
  }
}
