{
  "quiz": {
    "title": "Algebra 1 (Practice Exam 42)",
    "settings": {
      "timeLimit": "90min",
      "shuffleQuestions": true,
      "shuffleOptions": true
    },
    "questions": [
      {
        "type": "mcq",
        "question": "Evaluate the expression $4x^2 - 3y$ when $x = -3$ and $y = 6$.",
        "options": ["$18$", "$-18$", "$54$", "$-54$"],
        "answer": "A",
        "explanation": "$4(-3)^2 - 3(6) = 4(9) - 18 = 36 - 18 = 18$."
      },
      {
        "type": "mcq",
        "question": "Rationalize $\\frac{32}{\\sqrt{8}}$.",
        "options": ["$8\\sqrt{2}$", "$4\\sqrt{8}$", "$16\\sqrt{2}$", "$32\\sqrt{2}$"],
        "answer": "A",
        "explanation": "$\\frac{32}{\\sqrt{8}} \\cdot \\frac{\\sqrt{8}}{\\sqrt{8}} = \\frac{32\\sqrt{8}}{8} = 4\\sqrt{8} = 4 \\cdot 2\\sqrt{2} = 8\\sqrt{2}$."
      },
      {
        "type": "mcq",
        "question": "Simplify $\\frac{12\\sqrt{30}}{4\\sqrt{5}}$.",
        "options": ["$3\\sqrt{6}$", "$4\\sqrt{6}$", "$3\\sqrt{25}$", "$8\\sqrt{6}$"],
        "answer": "A",
        "explanation": "$\\frac{12}{4} = 3$, $\\sqrt{\\frac{30}{5}} = \\sqrt{6}$, result: $3\\sqrt{6}$."
      },
      {
        "type": "mcq",
        "question": "Solve $x^2 - 10x + 18 = 0$.",
        "options": ["$5 \\pm \\sqrt{7}$", "$-5 \\pm \\sqrt{7}$", "$10 \\pm \\sqrt{7}$", "$5 \\pm 2\\sqrt{7}$"],
        "answer": "A",
        "explanation": "$x = \\frac{10 \\pm \\sqrt{100-72}}{2} = \\frac{10 \\pm \\sqrt{28}}{2} = \\frac{10 \\pm 2\\sqrt{7}}{2} = 5 \\pm \\sqrt{7}$."
      },
      {
        "type": "mcq",
        "question": "A rectangle has length $4x+5$ and width $3x-2$. If the perimeter is 62, find $x$.",
        "options": ["$4$", "$5$", "$6$", "$3$"],
        "answer": "A",
        "explanation": "$2[(4x+5)+(3x-2)] = 2(7x+3) = 62 \\Rightarrow 7x+3=31 \\Rightarrow 7x=28 \\Rightarrow x=4$."
      },
      {
        "type": "mcq",
        "question": "Find the median of the data: 52, 16, 31, 43, 25, 37, 48.",
        "options": ["$37$", "$31$", "$43$", "$25$"],
        "answer": "A",
        "explanation": "Sorted: 16, 25, 31, 37, 43, 48, 52. Middle (4th) = 37."
      },
      {
        "type": "mcq",
        "question": "The average of 8, 12, 18, and $x$ is 14. What is $x$?",
        "options": ["$18$", "$16$", "$20$", "$14$"],
        "answer": "A",
        "explanation": "$(8+12+18+x)/4 = 14 \\Rightarrow 38+x = 56 \\Rightarrow x = 18$."
      },
      {
        "type": "mcq",
        "question": "Is $(5, 5)$ a solution to $y \\ge x$ and $y \\le x$?",
        "options": ["Yes", "No", "Only if $x$ is positive", "Only if $y$ is positive"],
        "answer": "A",
        "explanation": "$5 \\ge 5$ is true and $5 \\le 5$ is true, so yes."
      },
      {
        "type": "mcq",
        "question": "Solve: $3x - 2 > 10$ and $4x \\le 32$.",
        "options": ["$x > 4$ and $x \\le 8$", "$4 < x \\le 8$", "No solution", "Both A and B"],
        "answer": "D",
        "explanation": "$3x-2>10 \\Rightarrow 3x>12 \\Rightarrow x>4$; $4x \\le 32 \\Rightarrow x \\le 8$; so $4 < x \\le 8$."
      },
      {
        "type": "mcq",
        "question": "The system $y \\ge x$ and $y \\le x-1$ has how many solutions?",
        "options": ["$0$", "$1$", "Infinite", "$2$"],
        "answer": "A",
        "explanation": "No number can satisfy both $y \\ge x$ and $y \\le x-1$ because $x-1 < x$."
      },
      {
        "type": "mcq",
        "question": "A line passes through $(-6, 4)$ and $(2, 0)$. Find the gradient.",
        "options": ["$-\\frac{1}{2}$", "$\\frac{1}{2}$", "$-2$", "$2$"],
        "answer": "A",
        "explanation": "$m = \\frac{0-4}{2-(-6)} = \\frac{-4}{8} = -\\frac{1}{2}$."
      },
      {
        "type": "mcq",
        "question": "Find the $x$-intercept of $y = 5x - 25$.",
        "options": ["$(5, 0)$", "$(-5, 0)$", "$(0, -25)$", "$(25, 0)$"],
        "answer": "A",
        "explanation": "Set $y=0$: $0 = 5x - 25 \\Rightarrow 5x = 25 \\Rightarrow x = 5$."
      },
      {
        "type": "mcq",
        "question": "Find the $x$-intercept of $y = -2x + 14$.",
        "options": ["$(7, 0)$", "$(-7, 0)$", "$(0, 14)$", "$(14, 0)$"],
        "answer": "A",
        "explanation": "Set $y=0$: $0 = -2x + 14 \\Rightarrow 2x = 14 \\Rightarrow x = 7$."
      },
      {
        "type": "mcq",
        "question": "A jar contains 7 green, 5 yellow, and 3 purple marbles. What is the probability of picking a green or purple marble?",
        "options": ["$\\frac{2}{3}$", "$\\frac{1}{3}$", "$\\frac{10}{15}$", "$\\frac{7}{15}$"],
        "answer": "A",
        "explanation": "Total = 15, green/purple = 10, probability = $\\frac{10}{15} = \\frac{2}{3}$."
      },
      {
        "type": "mcq",
        "question": "Simplify $8(\\sqrt{2} - 4)$.",
        "options": ["$8\\sqrt{2} - 32$", "$8\\sqrt{2} - 4$", "$\\sqrt{16} - 32$", "$8\\sqrt{2} - 8$"],
        "answer": "A",
        "explanation": "Distribute: $8\\sqrt{2} - 32$."
      },
      {
        "type": "mcq",
        "question": "Simplify $\\sqrt{10}(2\\sqrt{2} + 3)$.",
        "options": ["$4\\sqrt{5} + 3\\sqrt{10}$", "$2\\sqrt{20} + 3\\sqrt{10}$", "$20 + 3\\sqrt{10}$", "$4\\sqrt{5} + 30$"],
        "answer": "A",
        "explanation": "$2\\sqrt{20} + 3\\sqrt{10} = 2 \\cdot 2\\sqrt{5} + 3\\sqrt{10} = 4\\sqrt{5} + 3\\sqrt{10}$."
      },
      {
        "type": "mcq",
        "question": "What is the value of $30 - (-10) + 15 - 45 - (20 - 25)$?",
        "options": ["$15$", "$-15$", "$5$", "$-5$"],
        "answer": "A",
        "explanation": "$20-25=-5$; $30+10+15-45+5 = 40+15-45+5 = 55-45+5 = 10+5 = 15$."
      },
      {
        "type": "mcq",
        "question": "Simplify: $6 + 8 \\cdot 5 - 3$.",
        "options": ["$43$", "$67$", "$37$", "$55$"],
        "answer": "A",
        "explanation": "$8 \\cdot 5 = 40$, $6+40-3 = 43$."
      },
      {
        "type": "mcq",
        "question": "Simplify: $15 - 3 \\cdot 4^2 + 25$.",
        "options": ["$-8$", "$28$", "$-2$", "$32$"],
        "answer": "A",
        "explanation": "$4^2 = 16$, $3 \\cdot 16 = 48$, $15-48+25 = -33+25 = -8$."
      },
      {
        "type": "mcq",
        "question": "Evaluate $\\frac{3x - 2y}{4y + x}$ if $x = -2$, $y = 3$.",
        "options": ["$-\\frac{6}{5}$", "$\\frac{6}{5}$", "$-\\frac{5}{6}$", "$\\frac{5}{6}$"],
        "answer": "A",
        "explanation": "$\\frac{-6-6}{12-2} = \\frac{-12}{10} = -\\frac{6}{5}$."
      },
      {
        "type": "mcq",
        "question": "Simplify: $\\frac{30 - 50}{5 - 7^2}$.",
        "options": ["$\\frac{5}{11}$", "$-\\frac{5}{11}$", "$\\frac{20}{44}$", "$-\\frac{20}{44}$"],
        "answer": "A",
        "explanation": "$30-50=-20$, $5-49=-44$, $\\frac{-20}{-44} = \\frac{20}{44} = \\frac{5}{11}$."
      },
      {
        "type": "mcq",
        "question": "Use distributive property: $-6(2x - 3) + 5x$.",
        "options": ["$-7x + 18$", "$-7x - 18$", "$17x + 18$", "$17x - 18$"],
        "answer": "A",
        "explanation": "$-12x + 18 + 5x = -7x + 18$."
      },
      {
        "type": "mcq",
        "question": "Simplify: $10y - 4 - 3(2y + 5)$.",
        "options": ["$4y - 19$", "$4y + 19$", "$16y - 19$", "$16y + 19$"],
        "answer": "A",
        "explanation": "$10y-4-6y-15 = 4y - 19$."
      },
      {
        "type": "mcq",
        "question": "Write in lowest terms: $\\frac{72a^5b^3c^2}{48a^4b^6c}$.",
        "options": ["$\\frac{3ac}{2b^3}$", "$\\frac{3a^2c}{2b^3}$", "$\\frac{3ac}{2b^2}$", "$\\frac{3ac^2}{2b^3}$"],
        "answer": "A",
        "explanation": "$\\frac{72}{48} = \\frac{3}{2}$, $a^5/a^4 = a$, $b^3/b^6 = 1/b^3$, $c^2/c = c$."
      },
      {
        "type": "mcq",
        "question": "Solve for $x$: $7(x - 4) = 21$.",
        "options": ["$7$", "$1$", "$-1$", "$3$"],
        "answer": "A",
        "explanation": "$x-4 = 3$, $x = 7$."
      },
      {
        "type": "mcq",
        "question": "Add: $(8m - 3n) + (-5m + 2n)$.",
        "options": ["$3m - n$", "$3m + n$", "$13m - n$", "$13m + n$"],
        "answer": "A",
        "explanation": "$8m-5m=3m$, $-3n+2n=-n$, result: $3m - n$."
      },
      {
        "type": "mcq",
        "question": "Subtract: $(6x^2 - 3x + 9) - (4x^2 + 2x - 7)$.",
        "options": ["$2x^2 - 5x + 16$", "$2x^2 - x + 16$", "$2x^2 - 5x + 2$", "$10x^2 - x + 2$"],
        "answer": "A",
        "explanation": "$6x^2-4x^2=2x^2$, $-3x-2x=-5x$, $9-(-7)=16$."
      },
      {
        "type": "mcq",
        "question": "Multiply: $(x^2 - 5x + 6)(x - 3)$.",
        "options": ["$x^3 - 8x^2 + 21x - 18$", "$x^3 - 2x^2 - 9x + 18$", "$x^3 - 8x^2 + 9x - 18$", "$x^3 - 5x^2 + 6x - 18$"],
        "answer": "A",
        "explanation": "$x^3-5x^2+6x-3x^2+15x-18 = x^3-8x^2+21x-18$."
      },
      {
        "type": "mcq",
        "question": "Seven more than twice a number is equal to three times the number minus four. Find the equation.",
        "options": ["$2x + 7 = 3x - 4$", "$2x - 7 = 3x - 4$", "$7x + 2 = 3x - 4$", "$2x + 7 = 3x + 4$"],
        "answer": "A",
        "explanation": "Let $x$ be number: $2x + 7 = 3x - 4$."
      },
      {
        "type": "mcq",
        "question": "Expand: $(5x + 2)^2$.",
        "options": ["$25x^2 + 20x + 4$", "$25x^2 + 4$", "$5x^2 + 20x + 4$", "$25x^2 + 10x + 4$"],
        "answer": "A",
        "explanation": "$(5x)^2 + 2(5x)(2) + 2^2 = 25x^2 + 20x + 4$."
      },
      {
        "type": "mcq",
        "question": "Which is smaller, $-\\frac{4}{5}$ or $-\\frac{7}{9}$?",
        "options": ["$-\\frac{4}{5}$", "$-\\frac{7}{9}$", "They are equal", "Cannot determine"],
        "answer": "A",
        "explanation": "$-\\frac{4}{5} = -0.8$, $-\\frac{7}{9} \\approx -0.777$, so $-\\frac{4}{5}$ is smaller."
      },
      {
        "type": "mcq",
        "question": "Evaluate $|9 - 16| - |4 - 13|$.",
        "options": ["$-2$", "$2$", "$-4$", "$4$"],
        "answer": "A",
        "explanation": "$|9-16| = 7$, $|4-13| = 9$, $7-9 = -2$."
      },
      {
        "type": "mcq",
        "question": "Solve: $8x - 5 \\le 7x + 4$.",
        "options": ["$x \\le 9$", "$x \\ge 9$", "$x \\le -9$", "$x \\ge -9$"],
        "answer": "A",
        "explanation": "$8x-7x \\le 4+5 \\Rightarrow x \\le 9$."
      },
      {
        "type": "mcq",
        "question": "Triangle sides: first $x$, second $3x-2$, third $2x+5$. Perimeter 39. Find equation.",
        "options": ["$x + (3x-2) + (2x+5) = 39$", "$x + 3x + 2x = 39$", "$(3x-2) + (2x+5) = 39$", "$x + (3x-2) = 39$"],
        "answer": "A",
        "explanation": "Sum of sides equals perimeter."
      },
      {
        "type": "mcq",
        "question": "If Alice has \\$40 less than three times what Bob has, and Bob has $B$, represent Alice's amount.",
        "options": ["$3B - 40$", "$40 - 3B$", "$3B + 40$", "$B - 40$"],
        "answer": "A",
        "explanation": "Three times Bob: $3B$, minus 40: $3B - 40$."
      },
      {
        "type": "mcq",
        "question": "Multiply: $5x(4x^2 - 3x + 2)$.",
        "options": ["$20x^3 - 15x^2 + 10x$", "$20x^3 - 15x^2 + 2$", "$20x^3 - 3x^2 + 10x$", "$9x^3 - 15x^2 + 10x$"],
        "answer": "A",
        "explanation": "$5x \\cdot 4x^2 = 20x^3$, $5x \\cdot (-3x) = -15x^2$, $5x \\cdot 2 = 10x$."
      },
      {
        "type": "mcq",
        "question": "Divide: $\\frac{36q^5 - 24q^4 + 12q^3}{6q^2}$.",
        "options": ["$6q^3 - 4q^2 + 2q$", "$6q^3 - 4q^2 + 12$", "$36q^3 - 4q^2 + 2q$", "$6q^3 - 24q^2 + 2q$"],
        "answer": "A",
        "explanation": "$36q^5/6q^2 = 6q^3$, $-24q^4/6q^2 = -4q^2$, $12q^3/6q^2 = 2q$."
      },
      {
        "type": "mcq",
        "question": "Factor completely: $12x^4 - 30x^3 + 18x^2$.",
        "options": ["$6x^2(2x-3)(x-1)$", "$6x^2(2x+3)(x-1)$", "$6x^2(2x-3)(x+1)$", "$12x^2(x-1)(x-3)$"],
        "answer": "A",
        "explanation": "GCF $6x^2$: $6x^2(2x^2 - 5x + 3) = 6x^2(2x-3)(x-1)$."
      },
      {
        "type": "mcq",
        "question": "Factor completely: $x^2 - 18x + 81$.",
        "options": ["$(x-9)^2$", "$(x+9)^2$", "$(x-9)(x+9)$", "$(x-18)^2$"],
        "answer": "A",
        "explanation": "Perfect square: $(x-9)^2$."
      },
      {
        "type": "mcq",
        "question": "Factor completely: $8x^2 - 8x - 48$.",
        "options": ["$8(x-3)(x+2)$", "$8(x+3)(x-2)$", "$8(x-4)(x+1)$", "$8(x-6)(x+1)$"],
        "answer": "A",
        "explanation": "GCF 8: $8(x^2 - x - 6) = 8(x-3)(x+2)$."
      },
      {
        "type": "mcq",
        "question": "Solve: $x^2 - 9x + 20 = 0$.",
        "options": ["$x = 4$ or $x = 5$", "$x = -4$ or $x = -5$", "$x = 2$ or $x = 10$", "$x = -2$ or $x = -10$"],
        "answer": "A",
        "explanation": "$(x-4)(x-5)=0$, so $x=4$ or $x=5$."
      },
      {
        "type": "mcq",
        "question": "Solve by factoring: $5x^2 - 15x = 0$.",
        "options": ["$x = 0$ or $x = 3$", "$x = 0$ or $x = -3$", "$x = 5$ or $x = 3$", "$x = 0$ only"],
        "answer": "A",
        "explanation": "$5x(x-3)=0$, so $x=0$ or $x=3$."
      },
      {
        "type": "mcq",
        "question": "Simplify: $\\frac{16x^2 - 64}{8x + 16}$.",
        "options": ["$2(x-2)$", "$2(x+2)$", "$\\frac{x-2}{2}$", "$\\frac{x+2}{2}$"],
        "answer": "A",
        "explanation": "$\\frac{16(x^2-4)}{8(x+2)} = \\frac{16(x-2)(x+2)}{8(x+2)} = 2(x-2)$."
      },
      {
        "type": "mcq",
        "question": "Given $2x - 5y = 10$, find $y$ for $(5, y)$.",
        "options": ["$0$", "$-5$", "$5$", "$2$"],
        "answer": "A",
        "explanation": "$2(5) - 5y = 10 \\Rightarrow 10 - 5y = 10 \\Rightarrow -5y = 0 \\Rightarrow y = 0$."
      },
      {
        "type": "mcq",
        "question": "Which property is shown by $3 \\times (4 \\times 5) = (3 \\times 4) \\times 5$?",
        "options": ["Associative Property of Multiplication", "Commutative Property of Multiplication", "Distributive Property", "Identity Property"],
        "answer": "A",
        "explanation": "This shows grouping doesn't matter, which is the associative property."
      }
    ]
  }
}

